valiotworkflows/__init__.py
valiotworkflows/__version__.py
valiotworkflows/async_utils.py
valiotworkflows/base_service_plugin_mixin.py
valiotworkflows/config.py
valiotworkflows/execution_mode.py
valiotworkflows/logging.py
valiotworkflows/mutations.py
valiotworkflows/plugins/__init__.py
valiotworkflows/plugins/graphql_sub_plugin.py
valiotworkflows/redis/__init__.py
valiotworkflows/redis/redis_base.py
valiotworkflows/redis/redis_client_factory.py
valiotworkflows/redis/valiot_redis_client.py
valiotworkflows/service_decorator.py
valiotworkflows/service_handler.py
valiotworkflows/service_handler_base.py
valiotworkflows/services.py
valiotworkflows/testing/__init__.py
valiotworkflows/utils/__init__.py
valiotworkflows/utils/compression.py
valiotworkflows/utils/compressor_mixin.py
valiotworkflows/utils/date_handling.py
valiotworkflows/utils/functions.py
valiotworkflows/utils/jwt_handling.py
valiotworkflows/utils/serialization.py
valiotworkflows/validations.py
valiotworkflows/workflows/__init__.py
valiotworkflows/workflows/decorator/__init__.py
valiotworkflows/workflows/decorator/category_definition.py
valiotworkflows/workflows/decorator/state_definition.py
valiotworkflows/workflows/decorator/utils.py
valiotworkflows/workflows/decorator/workflow_decorator.py
valiotworkflows/workflows/decorator/workflow_definition.py
valiotworkflows/workflows/events/__init__.py
valiotworkflows/workflows/events/workflow_event.py
valiotworkflows/workflows/gql_activities.py
valiotworkflows/workflows/mutations.py
valiotworkflows/workflows/temporal_workflow.py
valiotworkflows/workflows/utils.py
valiotworkflows/workflows/workflow_handle.py
valiotworkflows/workflows/workflow_handler.py
valiotworkflows/workflows/workflow_handler_base.py
valiotworkflows/workflows/workflow_object.py
valiotworkflows/workflows/workflow_setup.py
valiotworkflows/workflows/workflow_worker.py
valiotworkflows-1.4.0rc2.dist-info/METADATA
valiotworkflows-1.4.0rc2.dist-info/WHEEL
valiotworkflows-1.4.0rc2.dist-info/RECORD
