Metadata-Version: 2.1
Name: valiotworkflows
Version: 1.4.0rc2
Summary: Library to implement services and plugins for the Valiot Workflows framework
Author: Valiot
Author-email: adrian@valiot.io
Requires-Python: >=3.11,<4.0
Classifier: Programming Language :: Python :: 3
Classifier: Programming Language :: Python :: 3.11
Classifier: Programming Language :: Python :: 3.12
Requires-Dist: orjson (>=3.10.18,<4.0.0)
Requires-Dist: pydash (>=8.0,<9.0)
Requires-Dist: pygqlc (>=3.5.0,<4.0.0)
Requires-Dist: pyjwt (>=2.8.0,<3.0.0)
Requires-Dist: python-dateutil (>=2.8.2,<3.0.0)
Requires-Dist: pytz (>=2024.1,<2026.0)
Requires-Dist: redis[hiredis] (>=6.1.0,<7.0.0)
Requires-Dist: temporalio (>=1.8.0,<2.0.0)
Requires-Dist: valiotlogging (>=0.1.0,<2.0.0)
